{
  "train_results.elbo": -658.1166381835938,
  "train_results.kl_loss": 3.5120248794555664,
  "train_results.loss": 668.6529541015625,
  "train_results.reconstruction_loss": 654.6044311523438,
  "train_results.regularizer": 14.048099517822266,
  "train_results.global_step": 10000,
  "train_results.elapsed_time": 886.2592675685883,
  "train_results.uuid": "fc0f1376-c0fa-404b-9ec2-963caea328b5",
  "train_config.AdamOptimizer.beta1": "0.9",
  "train_config.AdamOptimizer.beta2": "0.999",
  "train_config.AdamOptimizer.epsilon": "1e-08",
  "train_config.AdamOptimizer.learning_rate": "0.0001",
  "train_config.AdamOptimizer.name": "'Adam'",
  "train_config.AdamOptimizer.use_locking": "False",
  "train_config.bernoulli_loss.subtract_true_image_entropy": "False",
  "train_config.dataset.name": "'scatt'",
  "train_config.decoder.decoder_fn": "@deconv_decoder",
  "train_config.encoder.encoder_fn": "@conv_encoder",
  "train_config.encoder.num_latent": "3",
  "train_config.export_as_tf_hub.drop_collections": "None",
  "train_config.model.batch_size": "16",
  "train_config.model.eval_steps": "1000",
  "train_config.model.model": "@vae()",
  "train_config.model.model_num": "None",
  "train_config.model.name": "''",
  "train_config.model.random_seed": "0",
  "train_config.model.training_steps": "10000",
  "train_config.reconstruction_loss.activation": "'logits'",
  "train_config.reconstruction_loss.loss_fn": "@bernoulli_loss",
  "train_config.vae.beta": "4",
  "train_config.vae_optimizer.learning_rate": "None",
  "train_config.vae_optimizer.optimizer_fn": "@AdamOptimizer"
}